Metadata-Version: 2.1
Name: bitsnbytes
Version: 1.0.0
Summary: Introduces the Bit, Nibble, Byte and ByteLike types
Home-page: UNKNOWN
Author: Sjoerd Vermeulen
Author-email: sjoerd@marsenaar.com
License: UNKNOWN
Platform: UNKNOWN
Classifier: Programming Language :: Python :: 3
Classifier: License :: OSI Approved :: MIT License
Classifier: Operating System :: OS Independent
Requires-Python: >=3.6
